Metadata-Version: 1.1
Name: elink-sdk
Version: 1.0.4
Summary: ELink SDK for python
Home-page: http://www.elinkgate.com
Author: ELinkGate
Author-email: kevin.truong@elinkgate.com
License: UNKNOWN
Platform: UNKNOWN
Classifier: Programming Language :: Python :: 3
Classifier: License :: OSI Approved :: MIT License
